{
  "version": "2.0.0",
  "totalPlanes": 9,
  "ultimaActualizacion": "2025-07-15T09:55:54.027Z",
  "planes": [
    {
      "referencia": "DMD-20250715-9689",
      "cliente": "Ramon Arias Abreu",
      "dni": "53849973G",
      "fecha": "2025-07-15T09:55:19.778Z",
      "estado": "contratado",
      "totalImporte": 0,
      "descuentoMedio": null,
      "cuotaMensual": 0,
      "ahorro": 0
    },
    {
      "referencia": "DMD-20250713-0149",
      "cliente": "Juan Perez Garcia",
      "dni": "12345678A",
      "fecha": "2025-07-13T17:14:57.635Z",
      "estado": "contratado",
      "totalImporte": 23000,
      "descuentoMedio": 18.369565217391305,
      "cuotaMensual": 1564.5833333333333,
      "ahorro": 4225
    },
    {
      "referencia": "DMD-20250710-1132",
      "cliente": "Ramon ARIAS",
      "dni": "53849973g",
      "fecha": "2025-07-10T09:40:43.467Z",
      "estado": "contratado",
      "totalImporte": 87857,
      "descuentoMedio": 50,
      "cuotaMensual": 3660.7083333333335,
      "ahorro": 43928.5
    },
    {
      "referencia": "DMD-20250710-8288",
      "cliente": "Humberto Gil",
      "dni": "53884469G",
      "fecha": "2025-07-10T08:11:27.209Z",
      "estado": "contratado",
      "totalImporte": 10221,
      "descuentoMedio": 18.268760395264653,
      "cuotaMensual": 174.03645833333334,
      "ahorro": 1867.25
    },
    {
      "referencia": "DMD-20250710-0293",
      "cliente": "Ramon Arias Abreu",
      "dni": "53849974G",
      "fecha": "2025-07-09T22:24:18.738Z",
      "estado": "contratado",
      "totalImporte": 8000,
      "descuentoMedio": 25,
      "cuotaMensual": 500,
      "ahorro": 2000
    },
    {
      "referencia": "DMD-20250710-7155",
      "cliente": "Ramon Arias Abreu",
      "dni": "53849973G",
      "fecha": "2025-07-09T22:22:16.862Z",
      "estado": "contratado",
      "totalImporte": 3000,
      "descuentoMedio": 36.666666666666664,
      "cuotaMensual": 126.66666666666667,
      "ahorro": 1100
    },
    {
      "referencia": "DMD-20250707-5847",
      "cliente": "Ramon Arias Abreu",
      "dni": "53849973G",
      "fecha": "2025-07-07T21:51:35.743Z",
      "estado": "contratado",
      "totalImporte": 4756,
      "totalConDescuento": 2611.4,
      "descuentoMedio": 45.092514718250634,
      "cuotaMensual": 174.09,
      "ahorro": 2144.6
    },
    {
      "referencia": "DMD-20250707-2905",
      "cliente": "ramon",
      "dni": "53849973G",
      "fecha": "2025-07-07T12:31:08.781Z",
      "estado": "en_negociacion",
      "totalImporte": 25852,
      "totalConDescuento": 20681.6,
      "descuentoMedio": 19.999999999999993,
      "cuotaMensual": 827.26,
      "ahorro": 5170.4
    },
    {
      "referencia": "DMD-20250707-4171",
      "cliente": "Ramon Arias Abreu",
      "dni": "53849973G",
      "fecha": "2025-07-07T12:29:27.659Z",
      "estado": "simulado",
      "totalImporte": 28329,
      "totalConDescuento": 25237.9,
      "descuentoMedio": 10.911433513360874,
      "cuotaMensual": 1577.37,
      "ahorro": 3091.1
    }
  ]
}